.gitignore
CMakeLists.txt
LICENSE
Readme.md
__init__.py
pyproject.toml
setup.cfg
setup.py
evaluation/Readme.md
evaluation/plot_results.py
evaluation/util.py
evaluation/artificial/interactive_segmentation.py
evaluation/conversion_scripts/crop_FastMRI.py
evaluation/conversion_scripts/crop_Larvae.py
evaluation/conversion_scripts/makemask_fim.py
evaluation/conversion_scripts/makemask_mri.py
evaluation/conversion_scripts/npy_to_png_slice.py
evaluation/conversion_scripts/save_h5_npy_png.py
evaluation/fastmri/data.py
evaluation/fastmri/illustration.py
evaluation/fastmri/interactive_segmentation.py
evaluation/fastmri/run_evaluation.py
evaluation/fim/data.py
evaluation/fim/illustration.py
evaluation/fim/run_evaluation.py
evaluation/spiral/data.py
evaluation/spiral/illustration.py
evaluation/spiral/run_evaluation.py
rw_noise.egg-info/PKG-INFO
rw_noise.egg-info/SOURCES.txt
rw_noise.egg-info/dependency_links.txt
rw_noise.egg-info/top_level.txt
src/imgs.cpp
src/imgs.h
src/lib.cpp
src/rw.cpp
src/rw.h
src/weights.cpp
src/weights.h