Metadata-Version: 2.1
Name: rw-noise
Version: 0.1.2
Summary: A library for random walker image segmentation under known noise models
Home-page: https://zivgitlab.uni-muenster.de/ag-pria/rw-noise-model
Author: Dominik Drees
Author-email: dominik.drees@uni-muenster.de
License: MIT
Keywords: random-walker image-segmentation noise-model
Platform: any
Classifier: Operating System :: OS Independent
Classifier: Operating System :: POSIX :: Linux
Classifier: Intended Audience :: Science/Research
Classifier: Programming Language :: C++
Classifier: Programming Language :: Python :: 3 :: Only
Classifier: License :: OSI Approved :: MIT License
License-File: LICENSE
